{
  "Header": {
    "WolvenKitVersion": "8.17.4",
    "WKitJsonVersion": "0.0.9",
    "GameVersion": 2310,
    "ExportedDateTime": "2026-04-28T10:16:36.0889174Z",
    "DataType": "CR2W",
    "ArchiveFileName": "H:\\projects\\Ghostline\\reference\\world\\000\\always_loaded_0.streamingsector"
  },
  "Data": {
    "Version": 195,
    "BuildVersion": 0,
    "RootChunk": {
      "$type": "worldStreamingSector",
      "category": "AlwaysLoaded",
      "cookingPlatform": "PLATFORM_PC",
      "externInplaceResource": {
        "DepotPath": {
          "$type": "ResourcePath",
          "$storage": "uint64",
          "$value": "0"
        },
        "Flags": "Soft"
      },
      "level": 255,
      "localInplaceResource": [],
      "nodeData": {
        "BufferId": "0",
        "Flags": 4063232,
        "Type": "WolvenKit.RED4.Archive.Buffer.worldNodeDataBuffer, WolvenKit.RED4, Version=8.17.4.0, Culture=neutral, PublicKeyToken=null",
        "Data": [
          {
            "Id": "0",
            "NodeIndex": 3269,
            "Position": {
              "$type": "Vector4",
              "W": 0,
              "X": -281.600037,
              "Y": -1982.36987,
              "Z": 8.92000198
            },
            "Orientation": {
              "$type": "Quaternion",
              "i": 0,
              "j": 0,
              "k": 0.507538378,
              "r": 0.861629128
            },
            "Scale": {
              "$type": "Vector3",
              "X": 1,
              "Y": 1,
              "Z": 1
            },
            "Pivot": {
              "$type": "Vector3",
              "X": 528.341187,
              "Y": -1497.7251,
              "Z": 208.841248
            },
            "Bounds": {
              "$type": "Box",
              "Max": {
                "$type": "Vector4",
                "W": 0,
                "X": -281.600037,
                "Y": -1982.36987,
                "Z": 8.92000198
              },
              "Min": {
                "$type": "Vector4",
                "W": 0,
                "X": -281.600037,
                "Y": -1982.36987,
                "Z": 8.92000198
              }
            },
            "QuestPrefabRefHash": {
              "$type": "NodeRef",
              "$storage": "string",
              "$value": "$/03_night_city/#c_santo_domingo/rancho_coronado/sdrc_03/sdrc_03_questdesign_prefabRC7AC4I/#mq003_pr_corpse/mq003_02_corpse_prefabW67T3JI/#mq003_02_sm_corpse"
            },
            "UkHash1": {
              "$type": "NodeRef",
              "$storage": "uint64",
              "$value": "0"
            },
            "CookedPrefabData": {
              "DepotPath": {
                "$type": "ResourcePath",
                "$storage": "uint64",
                "$value": "0"
              },
              "Flags": "Default"
            },
            "MaxStreamingDistance": 9513.75586,
            "UkFloat1": 512,
            "Uk10": 32,
            "Uk11": 512,
            "Uk12": 0,
            "Uk13": "0",
            "Uk14": "0"
          },
          {
            "Id": "0",
            "NodeIndex": 3273,
            "Position": {
              "$type": "Vector4",
              "W": 0,
              "X": -286.080139,
              "Y": -1950.68311,
              "Z": 8.96000099
            },
            "Orientation": {
              "$type": "Quaternion",
              "i": 0,
              "j": 0,
              "k": -0.923879623,
              "r": 0.382683367
            },
            "Scale": {
              "$type": "Vector3",
              "X": 1,
              "Y": 1,
              "Z": 1
            },
            "Pivot": {
              "$type": "Vector3",
              "X": 528.341187,
              "Y": -1497.7251,
              "Z": 208.841248
            },
            "Bounds": {
              "$type": "Box",
              "Max": {
                "$type": "Vector4",
                "W": 0,
                "X": -286.080139,
                "Y": -1950.68311,
                "Z": 8.96000099
              },
              "Min": {
                "$type": "Vector4",
                "W": 0,
                "X": -286.080139,
                "Y": -1950.68311,
                "Z": 8.96000099
              }
            },
            "QuestPrefabRefHash": {
              "$type": "NodeRef",
              "$storage": "string",
              "$value": "$/03_night_city/#c_santo_domingo/rancho_coronado/sdrc_03/sdrc_03_questdesign_prefabRC7AC4I/#mq003_pr_homeless/mq003_01_homeless_prefabR3S725Q/#mq003_01_sm_homeless"
            },
            "UkHash1": {
              "$type": "NodeRef",
              "$storage": "uint64",
              "$value": "0"
            },
            "CookedPrefabData": {
              "DepotPath": {
                "$type": "ResourcePath",
                "$storage": "uint64",
                "$value": "0"
              },
              "Flags": "Default"
            },
            "MaxStreamingDistance": 9513.75586,
            "UkFloat1": 512,
            "Uk10": 32,
            "Uk11": 512,
            "Uk12": 0,
            "Uk13": "0",
            "Uk14": "0"
          },
          {
            "Id": "0",
            "NodeIndex": 3277,
            "Position": {
              "$type": "Vector4",
              "W": 0,
              "X": -284.546295,
              "Y": -1895.73059,
              "Z": 8.77800083
            },
            "Orientation": {
              "$type": "Quaternion",
              "i": 0,
              "j": 0,
              "k": -0.999657333,
              "r": -0.0261768699
            },
            "Scale": {
              "$type": "Vector3",
              "X": 1,
              "Y": 1,
              "Z": 1
            },
            "Pivot": {
              "$type": "Vector3",
              "X": 528.341187,
              "Y": -1497.7251,
              "Z": 208.841248
            },
            "Bounds": {
              "$type": "Box",
              "Max": {
                "$type": "Vector4",
                "W": 0,
                "X": -284.546295,
                "Y": -1895.73059,
                "Z": 8.77800083
              },
              "Min": {
                "$type": "Vector4",
                "W": 0,
                "X": -284.546295,
                "Y": -1895.73059,
                "Z": 8.77800083
              }
            },
            "QuestPrefabRefHash": {
              "$type": "NodeRef",
              "$storage": "string",
              "$value": "$/03_night_city/#c_santo_domingo/rancho_coronado/sdrc_03/sdrc_03_questdesign_prefabRC7AC4I/#mq003_pr_homeless/#mq003_spwn"
            },
            "UkHash1": {
              "$type": "NodeRef",
              "$storage": "uint64",
              "$value": "0"
            },
            "CookedPrefabData": {
              "DepotPath": {
                "$type": "ResourcePath",
                "$storage": "uint64",
                "$value": "0"
              },
              "Flags": "Default"
            },
            "MaxStreamingDistance": 9513.75586,
            "UkFloat1": 512,
            "Uk10": 32,
            "Uk11": 512,
            "Uk12": 0,
            "Uk13": "0",
            "Uk14": "0"
          },
          {
            "Id": "0",
            "NodeIndex": 3291,
            "Position": {
              "$type": "Vector4",
              "W": 0,
              "X": -286.864685,
              "Y": -1951.24219,
              "Z": 11.031002
            },
            "Orientation": {
              "$type": "Quaternion",
              "i": 0,
              "j": 0,
              "k": -0.923879623,
              "r": 0.382683367
            },
            "Scale": {
              "$type": "Vector3",
              "X": 1,
              "Y": 1,
              "Z": 1
            },
            "Pivot": {
              "$type": "Vector3",
              "X": 528.341187,
              "Y": -1497.7251,
              "Z": 208.841248
            },
            "Bounds": {
              "$type": "Box",
              "Max": {
                "$type": "Vector4",
                "W": 0,
                "X": -286.864685,
                "Y": -1951.24219,
                "Z": 11.031002
              },
              "Min": {
                "$type": "Vector4",
                "W": 0,
                "X": -286.864685,
                "Y": -1951.24219,
                "Z": 11.031002
              }
            },
            "QuestPrefabRefHash": {
              "$type": "NodeRef",
              "$storage": "string",
              "$value": "$/03_night_city/#c_santo_domingo/rancho_coronado/sdrc_03/sdrc_03_questdesign_prefabRC7AC4I/#mq003_pr_homeless/#mq003_mp_homeless"
            },
            "UkHash1": {
              "$type": "NodeRef",
              "$storage": "uint64",
              "$value": "0"
            },
            "CookedPrefabData": {
              "DepotPath": {
                "$type": "ResourcePath",
                "$storage": "uint64",
                "$value": "0"
              },
              "Flags": "Default"
            },
            "MaxStreamingDistance": 9513.75586,
            "UkFloat1": 512,
            "Uk10": 32,
            "Uk11": 512,
            "Uk12": 0,
            "Uk13": "0",
            "Uk14": "0"
          }
        ]
      },
      "nodeRefs": [
        {
          "$type": "NodeRef",
          "$storage": "string",
          "$value": "$/03_night_city/se5/se5_questdesign_prefabDP7PGZY/#mq003_pr_orbital_pod/#mq003_com_corpo_squad"
        },
        {
          "$type": "NodeRef",
          "$storage": "string",
          "$value": "$/03_night_city/#c_santo_domingo/rancho_coronado/sdrc_03/sdrc_03_questdesign_prefabRC7AC4I/#mq003_pr_corpse/#mq003_tel_gas_station"
        },
        {
          "$type": "NodeRef",
          "$storage": "string",
          "$value": "$/03_night_city/#c_santo_domingo/rancho_coronado/sdrc_03/sdrc_03_questdesign_prefabRC7AC4I/#mq003_pr_homeless/#mq003_homeless_fat_end"
        },
        {
          "$type": "NodeRef",
          "$storage": "string",
          "$value": "$/03_night_city/#c_santo_domingo/rancho_coronado/sdrc_03/sdrc_03_questdesign_prefabRC7AC4I/#mq003_pr_corpse/mq003_02_corpse_prefabW67T3JI/#mq003_02_sm_corpse"
        },
        {
          "$type": "NodeRef",
          "$storage": "string",
          "$value": "$/03_night_city/#c_santo_domingo/rancho_coronado/sdrc_03/sdrc_03_questdesign_prefabRC7AC4I/#mq003_pr_homeless/#mq003_tr_homeless_case_mood"
        },
        {
          "$type": "NodeRef",
          "$storage": "string",
          "$value": "$/03_night_city/#c_santo_domingo/rancho_coronado/sdrc_03/sdrc_03_questdesign_prefabRC7AC4I/#mq003_pr_homeless/#mq003_tr_prevention_deescalate"
        },
        {
          "$type": "NodeRef",
          "$storage": "string",
          "$value": "$/03_night_city/#c_santo_domingo/rancho_coronado/sdrc_03/sdrc_03_gameplay_prefabM3YZY5I/#sdrc_03_devices/#mq003_suitcase"
        },
        {
          "$type": "NodeRef",
          "$storage": "string",
          "$value": "$/03_night_city/#c_santo_domingo/rancho_coronado/sdrc_03/sdrc_03_questdesign_prefabRC7AC4I/#mq003_pr_homeless/#mq003_homeless_leader_start"
        },
        {
          "$type": "NodeRef",
          "$storage": "string",
          "$value": "$/03_night_city/#c_santo_domingo/rancho_coronado/sdrc_03/sdrc_03_questdesign_prefabRC7AC4I/#mq003_pr_homeless/mq003_01_homeless_prefabR3S725Q/#mq003_01_sm_homeless"
        },
        {
          "$type": "NodeRef",
          "$storage": "string",
          "$value": "$/03_night_city/#c_santo_domingo/rancho_coronado/sdrc_03/sdrc_03_questdesign_prefabRC7AC4I/#mq003_pr_homeless/#mq003_ws_parking_002"
        },
        {
          "$type": "NodeRef",
          "$storage": "string",
          "$value": "$/03_night_city/#c_santo_domingo/rancho_coronado/sdrc_03/sdrc_03_questdesign_prefabRC7AC4I/#mq003_pr_homeless/#mq003_tr_engage_homeless"
        },
        {
          "$type": "NodeRef",
          "$storage": "string",
          "$value": "$/03_night_city/#c_santo_domingo/rancho_coronado/sdrc_03/sdrc_03_questdesign_prefabRC7AC4I/#mq003_pr_homeless/#mq003_tr_someone_coming"
        },
        {
          "$type": "NodeRef",
          "$storage": "string",
          "$value": "$/03_night_city/#c_santo_domingo/rancho_coronado/sdrc_03/sdrc_03_questdesign_prefabRC7AC4I/#mq003_pr_homeless/#mq003_spwn"
        },
        {
          "$type": "NodeRef",
          "$storage": "string",
          "$value": "$/03_night_city/#c_santo_domingo/rancho_coronado/sdrc_03/sdrc_03_questdesign_prefabRC7AC4I/#mq003_pr_homeless/#mq003_homeless_leader_scared"
        },
        {
          "$type": "NodeRef",
          "$storage": "string",
          "$value": "$/03_night_city/#c_santo_domingo/rancho_coronado/sdrc_03/sdrc_03_questdesign_prefabRC7AC4I/#mq003_pr_homeless/#mq003_tr_corpse_found"
        },
        {
          "$type": "NodeRef",
          "$storage": "string",
          "$value": "$/03_night_city/#c_santo_domingo/rancho_coronado/sdrc_03/sdrc_03_questdesign_prefabRC7AC4I/#mq003_pr_homeless/#mq003_homeless_fat_scared"
        },
        {
          "$type": "NodeRef",
          "$storage": "string",
          "$value": "$/03_night_city/#c_santo_domingo/rancho_coronado/sdrc_03/sdrc_03_questdesign_prefabRC7AC4I/#mq003_pr_homeless/#mq003_tr_forbiddenarea"
        },
        {
          "$type": "NodeRef",
          "$storage": "string",
          "$value": "$/03_night_city/#c_santo_domingo/rancho_coronado/sdrc_03/sdrc_03_questdesign_prefabRC7AC4I/#mq003_pr_homeless/#mq003_homeless_suitcase_start"
        },
        {
          "$type": "NodeRef",
          "$storage": "string",
          "$value": "$/03_night_city/#c_santo_domingo/rancho_coronado/sdrc_03/sdrc_03_questdesign_prefabRC7AC4I/#mq003_pr_homeless/#mq003_spl_homeless_suitcase_end"
        },
        {
          "$type": "NodeRef",
          "$storage": "string",
          "$value": "$/03_night_city/#c_santo_domingo/rancho_coronado/sdrc_03/sdrc_03_questdesign_prefabRC7AC4I/#mq003_pr_homeless/#mq003_spl_homeless_leader_end"
        },
        {
          "$type": "NodeRef",
          "$storage": "string",
          "$value": "$/03_night_city/#c_santo_domingo/rancho_coronado/sdrc_03/sdrc_03_questdesign_prefabRC7AC4I/#mq003_pr_corpse/#mq003_tr_02_corpse_area"
        },
        {
          "$type": "NodeRef",
          "$storage": "string",
          "$value": "$/03_night_city/#c_santo_domingo/rancho_coronado/sdrc_03/sdrc_03_questdesign_prefabRC7AC4I/#mq003_pr_homeless/#mq003_homeless_suitcase_scared"
        },
        {
          "$type": "NodeRef",
          "$storage": "string",
          "$value": "$/03_night_city/#c_santo_domingo/rancho_coronado/sdrc_03/sdrc_03_questdesign_prefabRC7AC4I/#mq003_pr_homeless/#mq003_homeless_fat_start"
        },
        {
          "$type": "NodeRef",
          "$storage": "string",
          "$value": "$/03_night_city/se5/#s5_gameplay/#mq003_drop_pod_landed"
        },
        {
          "$type": "NodeRef",
          "$storage": "string",
          "$value": "$/03_night_city/#c_santo_domingo/rancho_coronado/sdrc_03/sdrc_03_questdesign_prefabRC7AC4I/#mq003_pr_homeless/#mq003_homeless_leader_end"
        },
        {
          "$type": "NodeRef",
          "$storage": "string",
          "$value": "$/03_night_city/#c_santo_domingo/rancho_coronado/sdrc_03/sdrc_03_questdesign_prefabRC7AC4I/#mq003_pr_homeless/#mq003_tr_cin_setup"
        },
        {
          "$type": "NodeRef",
          "$storage": "string",
          "$value": "$/03_night_city/#c_santo_domingo/rancho_coronado/sdrc_03/sdrc_03_questdesign_prefabRC7AC4I/#mq003_pr_homeless/#mq003_spl_homeless_fat_end"
        },
        {
          "$type": "NodeRef",
          "$storage": "string",
          "$value": "$/03_night_city/#c_santo_domingo/rancho_coronado/sdrc_03/sdrc_03_questdesign_prefabRC7AC4I/#mq003_pr_homeless/#mq003_ws_parking_01"
        },
        {
          "$type": "NodeRef",
          "$storage": "string",
          "$value": "$/03_night_city/#c_santo_domingo/rancho_coronado/sdrc_03/sdrc_03_questdesign_prefabRC7AC4I/#mq003_pr_homeless/#mq003_com_homeless"
        },
        {
          "$type": "NodeRef",
          "$storage": "string",
          "$value": "$/03_night_city/#c_santo_domingo/rancho_coronado/sdrc_03/sdrc_03_gameplay_prefabM3YZY5I/#sdrc_03_devices/#mq003_corpse"
        },
        {
          "$type": "NodeRef",
          "$storage": "string",
          "$value": "$/03_night_city/#c_santo_domingo/rancho_coronado/sdrc_03/sdrc_03_questdesign_prefabRC7AC4I/#mq003_pr_homeless/#mq003_homeless_suitcase_end"
        },
        {
          "$type": "NodeRef",
          "$storage": "string",
          "$value": "$/03_night_city/#c_santo_domingo/rancho_coronado/sdrc_03/sdrc_03_questdesign_prefabRC7AC4I/#mq003_pr_homeless/#mq003_mp_homeless"
        }
      ],
      "nodes": [],
      "persistentNodeIndex": 0,
      "persistentNodes": [],
      "variantIndices": [0
      ],
      "variantNodes": [],
      "version": 62
    },
    "EmbeddedFiles": []
  }
}