{
  "Header": {
    "WolvenKitVersion": "8.17.4-nightly.2026-03-20",
    "WKitJsonVersion": "0.0.9",
    "GameVersion": 2310,
    "ExportedDateTime": "2026-03-22T13:52:45.0668019Z",
    "DataType": "CR2W",
    "ArchiveFileName": "C:\\Users\\user\\Documents\\templates\\source\\archive\\base\\journal\\cooked_journal.journal"
  },
  "Data": {
    "Version": 195,
    "BuildVersion": 0,
    "RootChunk": {
      "$type": "gameJournalResource",
      "cookingPlatform": "PLATFORM_PC",
      "entry": {
        "HandleId": "0",
        "Data": {
          "$type": "gameJournalRootFolderEntry",
          "descriptor": {
            "DepotPath": {
              "$type": "ResourcePath",
              "$storage": "string",
              "$value": "base\\journal\\descriptor.journaldesc"
            },
            "Flags": "Soft"
          },
          "entries": [
            {
              "HandleId": "26250",
              "Data": {
                "$type": "gameJournalPrimaryFolderEntry",
                "entries": [
                  {
                    "HandleId": "28431",
                    "Data": {
                      "$type": "gameJournalContact",
                      "avatarID": {
                        "$type": "TweakDBID",
                        "$storage": "string",
                        "$value": "PhoneAvatars.Avatar_Red_menace"
                      },
                      "entries": [
                        {
                          "HandleId": "28432",
                          "Data": {
                            "$type": "gameJournalPhoneConversation",
                            "entries": [
                              {
                                "HandleId": "28433",
                                "Data": {
                                  "$type": "gameJournalPhoneMessage",
                                  "attachment": null,
                                  "delay": 3,
                                  "id": "mq028_dead_01_dead",
                                  "imageId": {
                                    "$type": "TweakDBID",
                                    "$storage": "uint64",
                                    "$value": "0"
                                  },
                                  "isQuestImportant": 0,
                                  "journalEntryOverrideDataList": [],
                                  "sender": "NPC",
                                  "text": {
                                    "unk1": "0",
                                    "value": "LocKey#14146"
                                  }
                                }
                              },
                              {
                                "HandleId": "28434",
                                "Data": {
                                  "$type": "gameJournalPhoneMessage",
                                  "attachment": null,
                                  "delay": 3,
                                  "id": "mq028_dead_02_bmdead",
                                  "imageId": {
                                    "$type": "TweakDBID",
                                    "$storage": "uint64",
                                    "$value": "0"
                                  },
                                  "isQuestImportant": 0,
                                  "journalEntryOverrideDataList": [],
                                  "sender": "NPC",
                                  "text": {
                                    "unk1": "0",
                                    "value": "LocKey#14147"
                                  }
                                }
                              },
                              {
                                "HandleId": "28435",
                                "Data": {
                                  "$type": "gameJournalPhoneMessage",
                                  "attachment": null,
                                  "delay": 3,
                                  "id": "mq028_dead_03_fail",
                                  "imageId": {
                                    "$type": "TweakDBID",
                                    "$storage": "uint64",
                                    "$value": "0"
                                  },
                                  "isQuestImportant": 0,
                                  "journalEntryOverrideDataList": [],
                                  "sender": "NPC",
                                  "text": {
                                    "unk1": "0",
                                    "value": "LocKey#14148"
                                  }
                                }
                              },
                              {
                                "HandleId": "28436",
                                "Data": {
                                  "$type": "gameJournalPhoneMessage",
                                  "attachment": null,
                                  "delay": 3,
                                  "id": "mq028_dead_04_failbm",
                                  "imageId": {
                                    "$type": "TweakDBID",
                                    "$storage": "uint64",
                                    "$value": "0"
                                  },
                                  "isQuestImportant": 0,
                                  "journalEntryOverrideDataList": [],
                                  "sender": "NPC",
                                  "text": {
                                    "unk1": "0",
                                    "value": "LocKey#14149"
                                  }
                                }
                              },
                              {
                                "HandleId": "28437",
                                "Data": {
                                  "$type": "gameJournalPhoneMessage",
                                  "attachment": null,
                                  "delay": 3,
                                  "id": "mq028_dead_05_failure",
                                  "imageId": {
                                    "$type": "TweakDBID",
                                    "$storage": "uint64",
                                    "$value": "0"
                                  },
                                  "isQuestImportant": 0,
                                  "journalEntryOverrideDataList": [],
                                  "sender": "NPC",
                                  "text": {
                                    "unk1": "0",
                                    "value": "LocKey#14150"
                                  }
                                }
                              },
                              {
                                "HandleId": "28438",
                                "Data": {
                                  "$type": "gameJournalPhoneChoiceGroup",
                                  "entries": [
                                    {
                                      "HandleId": "28439",
                                      "Data": {
                                        "$type": "gameJournalPhoneChoiceEntry",
                                        "id": "mq028_dead_07_wrong",
                                        "isQuestImportant": 1,
                                        "journalEntryOverrideDataList": [],
                                        "questCondition": null,
                                        "text": {
                                          "unk1": "0",
                                          "value": "LocKey#14151"
                                        }
                                      }
                                    },
                                    {
                                      "HandleId": "28440",
                                      "Data": {
                                        "$type": "gameJournalPhoneChoiceEntry",
                                        "id": "mq028_dead_6b_whaaat",
                                        "isQuestImportant": 1,
                                        "journalEntryOverrideDataList": [],
                                        "questCondition": null,
                                        "text": {
                                          "unk1": "0",
                                          "value": "LocKey#14152"
                                        }
                                      }
                                    }
                                  ],
                                  "id": "mq028_dead_06_ch_wrong",
                                  "journalEntryOverrideDataList": []
                                }
                              },
                              {
                                "HandleId": "28441",
                                "Data": {
                                  "$type": "gameJournalPhoneMessage",
                                  "attachment": null,
                                  "delay": 3,
                                  "id": "mq028_dead_07_wrong",
                                  "imageId": {
                                    "$type": "TweakDBID",
                                    "$storage": "uint64",
                                    "$value": "0"
                                  },
                                  "isQuestImportant": 0,
                                  "journalEntryOverrideDataList": [],
                                  "sender": "NPC",
                                  "text": {
                                    "unk1": "0",
                                    "value": "LocKey#14155"
                                  }
                                }
                              },
                              {
                                "HandleId": "28442",
                                "Data": {
                                  "$type": "gameJournalPhoneMessage",
                                  "attachment": null,
                                  "delay": 3,
                                  "id": "mq028_dead_08_stalker",
                                  "imageId": {
                                    "$type": "TweakDBID",
                                    "$storage": "uint64",
                                    "$value": "0"
                                  },
                                  "isQuestImportant": 0,
                                  "journalEntryOverrideDataList": [],
                                  "sender": "NPC",
                                  "text": {
                                    "unk1": "0",
                                    "value": "LocKey#14156"
                                  }
                                }
                              },
                              {
                                "HandleId": "28443",
                                "Data": {
                                  "$type": "gameJournalPhoneChoiceGroup",
                                  "entries": [
                                    {
                                      "HandleId": "28444",
                                      "Data": {
                                        "$type": "gameJournalPhoneChoiceEntry",
                                        "id": "mq028_dead_6b_whaaat",
                                        "isQuestImportant": 1,
                                        "journalEntryOverrideDataList": [],
                                        "questCondition": null,
                                        "text": {
                                          "unk1": "0",
                                          "value": "LocKey#14153"
                                        }
                                      }
                                    },
                                    {
                                      "HandleId": "28445",
                                      "Data": {
                                        "$type": "gameJournalPhoneChoiceEntry",
                                        "id": "mq028_dead_06c_sorry",
                                        "isQuestImportant": 1,
                                        "journalEntryOverrideDataList": [],
                                        "questCondition": null,
                                        "text": {
                                          "unk1": "0",
                                          "value": "LocKey#14154"
                                        }
                                      }
                                    }
                                  ],
                                  "id": "mq028_dead_06b_ch_whaat",
                                  "journalEntryOverrideDataList": []
                                }
                              },
                              {
                                "HandleId": "28446",
                                "Data": {
                                  "$type": "gameJournalPhoneMessage",
                                  "attachment": null,
                                  "delay": 3,
                                  "id": "mq028_dead_09_face",
                                  "imageId": {
                                    "$type": "TweakDBID",
                                    "$storage": "uint64",
                                    "$value": "0"
                                  },
                                  "isQuestImportant": 0,
                                  "journalEntryOverrideDataList": [],
                                  "sender": "NPC",
                                  "text": {
                                    "unk1": "0",
                                    "value": "LocKey#14157"
                                  }
                                }
                              },
                              {
                                "HandleId": "28447",
                                "Data": {
                                  "$type": "gameJournalPhoneChoiceGroup",
                                  "entries": [
                                    {
                                      "HandleId": "28448",
                                      "Data": {
                                        "$type": "gameJournalPhoneChoiceEntry",
                                        "id": "mq028_dead_10a_deeplysorry",
                                        "isQuestImportant": 1,
                                        "journalEntryOverrideDataList": [],
                                        "questCondition": null,
                                        "text": {
                                          "unk1": "0",
                                          "value": "LocKey#14158"
                                        }
                                      }
                                    },
                                    {
                                      "HandleId": "28449",
                                      "Data": {
                                        "$type": "gameJournalPhoneChoiceEntry",
                                        "id": "mq028_dead_10b_anything",
                                        "isQuestImportant": 1,
                                        "journalEntryOverrideDataList": [],
                                        "questCondition": null,
                                        "text": {
                                          "unk1": "0",
                                          "value": "LocKey#14159"
                                        }
                                      }
                                    },
                                    {
                                      "HandleId": "28450",
                                      "Data": {
                                        "$type": "gameJournalPhoneChoiceEntry",
                                        "id": "mq028_dead_10c_yourfault",
                                        "isQuestImportant": 1,
                                        "journalEntryOverrideDataList": [],
                                        "questCondition": null,
                                        "text": {
                                          "unk1": "0",
                                          "value": "LocKey#14160"
                                        }
                                      }
                                    },
                                    {
                                      "HandleId": "28451",
                                      "Data": {
                                        "$type": "gameJournalPhoneChoiceEntry",
                                        "id": "mq028_dead_10d_whatever",
                                        "isQuestImportant": 1,
                                        "journalEntryOverrideDataList": [],
                                        "questCondition": null,
                                        "text": {
                                          "unk1": "0",
                                          "value": "LocKey#14161"
                                        }
                                      }
                                    }
                                  ],
                                  "id": "mq028_dead_10_ch_conclusion",
                                  "journalEntryOverrideDataList": []
                                }
                              },
                              {
                                "HandleId": "28452",
                                "Data": {
                                  "$type": "gameJournalPhoneMessage",
                                  "attachment": null,
                                  "delay": 3,
                                  "id": "mq028_dead_11_deeplysorry",
                                  "imageId": {
                                    "$type": "TweakDBID",
                                    "$storage": "uint64",
                                    "$value": "0"
                                  },
                                  "isQuestImportant": 0,
                                  "journalEntryOverrideDataList": [],
                                  "sender": "NPC",
                                  "text": {
                                    "unk1": "0",
                                    "value": "LocKey#14162"
                                  }
                                }
                              },
                              {
                                "HandleId": "28453",
                                "Data": {
                                  "$type": "gameJournalPhoneMessage",
                                  "attachment": null,
                                  "delay": 3,
                                  "id": "mq028_dead_11b_anything",
                                  "imageId": {
                                    "$type": "TweakDBID",
                                    "$storage": "uint64",
                                    "$value": "0"
                                  },
                                  "isQuestImportant": 0,
                                  "journalEntryOverrideDataList": [],
                                  "sender": "NPC",
                                  "text": {
                                    "unk1": "0",
                                    "value": "LocKey#14163"
                                  }
                                }
                              },
                              {
                                "HandleId": "28454",
                                "Data": {
                                  "$type": "gameJournalPhoneMessage",
                                  "attachment": null,
                                  "delay": 3,
                                  "id": "mq028_dead_11c_choke",
                                  "imageId": {
                                    "$type": "TweakDBID",
                                    "$storage": "uint64",
                                    "$value": "0"
                                  },
                                  "isQuestImportant": 0,
                                  "journalEntryOverrideDataList": [],
                                  "sender": "NPC",
                                  "text": {
                                    "unk1": "0",
                                    "value": "LocKey#14164"
                                  }
                                }
                              }
                            ],
                            "id": "mq028_dead",
                            "journalEntryOverrideDataList": [],
                            "title": {
                              "unk1": "0",
                              "value": "LocKey#48612"
                            }
                          }
                        }
                      ],
                      "id": "red_menace",
                      "isCallableDefault": 0,
                      "journalEntryOverrideDataList": [],
                      "name": {
                        "unk1": "0",
                        "value": "LocKey#10890"
                      },
                      "type": "Texter",
                      "useFlatMessageLayout": 1
                    }
                  }
                ],
                "id": "contacts",
                "journalEntryOverrideDataList": []
              }
            }
          ],
          "id": "",
          "journalEntryOverrideDataList": []
        }
      }
    },
    "EmbeddedFiles": []
  }
}